src/__init__.py
src/cross_validation/__init__.py
src/cross_validation/cross_validation.py
tests/__init__.py
tests/test_cross_validation.py
cross_validation_package-1.0.0.dist-info/LICENSE
cross_validation_package-1.0.0.dist-info/METADATA
cross_validation_package-1.0.0.dist-info/WHEEL
cross_validation_package-1.0.0.dist-info/top_level.txt
cross_validation_package-1.0.0.dist-info/RECORD
