Metadata-Version: 2.1
Name: cross-validation-package
Version: 1.0.0
Home-page: https://github.com/matteo-serafino/cross-validation.git
Author: Matteo Serafino
Author-email: matteo.serafino1@gmail.com
License: MIT
Keywords: cross-validation
Requires-Python: >=3.6.2
License-File: LICENSE
Requires-Dist: matplotlib (>=3.5.2)
Requires-Dist: numpy (>=1.23.1)
Requires-Dist: pandas (>=1.4.3)
Requires-Dist: ReliefF (>=0.1.2)
Requires-Dist: scikit-learn (>=1.1.1)
Requires-Dist: seaborn (>=0.11.2)
Requires-Dist: sklearn (>=0.0)
